Workbook

Sheet Marketplace Tasks
A1: Task ID | B1: Phase | C1: Type | D1: Task Title | E1: Description | F1: Reference (if any) | G1: Assigned To | H1: Status | I1: Notes
A2: TSK-001 | B2: Phase 0 - Foundations | C2: Backend | D2: Design seller identity model | E2: Decide whether sellers can be individual creators (not just verified brands) before writing the catalog service — this changes several foreign keys. | F2: m
A3: TSK-002 | B3: Phase 0 - Foundations | C3: Backend | D3: Migration: merch_products & merch_variants tables | E3: Create merch_products and merch_variants tables (SKU, size/color variants, pricing in INR/USD cents, stock_qty, weight, print_file_url, artwork_id link). | F3: Section 04 - Schema additions
A4: TSK-003 | B4: Phase 0 - Foundations | C4: Backend | D4: Migration: print_providers table | E4: Create print_providers table to store POD partner config (Printful/Printify/manual) with integration_type and api_config jsonb. | F4: Section 04 - Schema additions
A5: TSK-004 | B5: Phase 0 - Foundations | C5: Backend | D5: Seller onboarding API + KYC service | E5: Build onboarding API endpoints for new sellers, reusing brand_verification_requests pattern for KYC/KYB where applicable. | F5: Section 01 - Existing INFRA / Section 07 Q1
A6: TSK-005 | B6: Phase 0 - Foundations | C6: Frontend | D6: Seller onboarding UI flow | E6: Build the multi-step seller onboarding screens (profile, payout details, KYC document upload, verification status) consuming the onboarding API. | F6: Section 01 - Existing INFRA / Section 07 Q1
A7: TSK-006 | B7: Phase 0 - Foundations | C7: Frontend | D7: Seller dashboard shell | E7: Scaffold the seller dashboard shell/navigation (products, orders, payouts placeholders) that later phases will fill in. | F7: Section 06 - Phase 0 deliverables
A8: TSK-007 | B8: Phase 1 - Standalone Merch | C8: Backend | D8: Build carts & cart_items tables + API | E8: Create carts and cart_items tables and CRUD endpoints to support persistent multi-item, multi-seller shopping carts (item_type: license or merch_variant). | F8: Section 04 - Checkout schema
A9: TSK-008 | B9: Phase 1 - Standalone Merch | C9: Backend | D9: Split order_items by seller_id | E9: Add seller_id, item_type, merch_variant_id, and cart_id columns to orders/order_items so a single order can span multiple sellers. | F9: Section 04 - Checkout schema
A10: TSK-009 | B10: Phase 1 - Standalone Merch | C10: Backend | D10: Build addresses table + API | E10: Create addresses table and endpoints for buyer shipping addresses (line1/2, city, state, postal_code, country, is_default). | F10: Section 04 - Fulfillment schema
A11: TSK-010 | B11: Phase 1 - Standalone Merch | C11: Backend | D11: Build fulfillments table + manual status update API | E11: Create fulfillments and fulfillment_items tables with manual status update endpoints (fulfillment_type = in_house_stock, no POD integration yet). | F11: Section 06 - Phase 1 deliverables
A12: TSK-011 | B12: Phase 1 - Standalone Merch | C12: Backend | D12: Merch catalog listing API | E12: Build read APIs for browsing/searching the small standalone merch catalog (product + variant listing, filters). | F12: Section 06 - Phase 1
A13: TSK-012 | B13: Phase 1 - Standalone Merch | C13: Frontend | D13: Merch catalog browse & product detail pages | E13: Build the storefront pages for browsing merch products, filtering, and viewing a product detail page with variant (size/color) selection. | F13: Section 06 - Phase 1
... A35: TSK-034 | B35: Cross-cutting / Open Questions | C35: Frontend | D35: API contract review with frontend team | E35: Frontend sync with backend on request/response shapes for cart, checkout, fulfillment, and payouts endpoints before UI build-out per phase. | F35: Section 05 - Service boundaries diagram

Sheet Log Tracker
B1: Dev Log & Tracker
B3: Sprint Week | C3: Task ID/Name | D3: Feature / Project Area | E3: Task Description | F3: Priority | G3: Assigned To | H3: Status | I3: Reviewer | J3: Start Date | K3: Target Completion Date | L3: Completion Date | M3: Pull Request / Merge Link | N3: Progress Notes | O3: Blockers / Issues | P3: Next Steps | Q3: Carry Over to Next Week (Y/N)
B4: 46174 | C4: Dev Log & Tracker | D4: Project Management | E4: Create a spreadsheet for tracking development progress weekly and logging changes to the platform code. | F4: Medium | G4: Joey | H4: Complete | J4: 46174 | K4: 46174 | L4: 46174 | M4: N/A | N4: Completed after our meeting, sent to the team | O4: N/A | P4: Whole team gets on board and starts using this weekly. | Q4: Y
B5: June 5 push | C5: Double footer | D5: Navigation/Menu | E5: Fix the double footers that pop up on multiple pages. | F5: High | G5: Rafay | H5: Complete | J5: 46174 | K5: 46178 | L5: 46181
B6: June 5 push | C6: Update Buttons | D6: Home Page | E6: Buttons: for brands, artists, view active | F6: High | G6: Rafay | H6: Complete | J6: 46174 | K6: 46178 | L6: 46181
B7: June 5 push | C7: Artist Logos | D7: About | E7: Remove empty artist logos | F7: Medium | G7: Rafay | H7: Complete | J7: 46174 | K7: 46178 | L7: 46181
C8: Brand Properties listed | D8: Super Admin | E8: Have Brand properties listed under brand owners | F8: Low | G8: Dhruv | H8: Complete
C9: artist button 404 | D9: Super Admin | E9: artist button 404 fix | F9: Low | G9: Dhruv | H9: Complete
C10: Owner Profile | D10: Brand, Super Admin | E10: Owner profile separate from Brands tab | F10: Low | G10: Dhruv | H10: Complete
C11: Header/Footer | D11: Brand, Navigation/Menu | E11: No header and footer | F11: Low | G11: Rafay | H11: Complete
B12: 46174 | C12: Website Content Doc | D12: Website Content | E12: Create a doc with content for Dhruv to update including: past campaigns, fan artist users, licensed fan work, etc. | F12: High | G12: Joey | H12: In Progress | J12: 46174 | K12: 46175 | M12: N/A
B13: June 5 push | C13: Nav Bar update | D13: Navigation/Menu | E13: Fix Nav bar to be correct pages in web | F13: High | G13: Rafay | H13: Complete | J13: 46174 | L13: 46181 | N13: Desktop verson is complete but mobile version is still old nav bar options.
B14: June 5 push | C14: Button Hover | D14: About | E14: Remove button hover | F14: Medium | G14: Rafay | H14: Complete
B15: June 12 push | C15: Update Image | D15: Guidelines | E15: Update images with ones provided in Whatsapp group | F15: High | G15: Pratyank | H15: Complete | J15: 46181 | L15: 46202
B16: June 12 push | C16: Remove some sections | D16: Guidelines | E16: Remove following sections: Popular IP-Specific Guidelines, Additional Resources | F16: High | G16: Rafay | H16: Complete | J16: 46181 | L16: 46202
B17: June 12 push | C17: Discord link | D17: Guidelines | E17: keep artist community link and add Discord link | F17: Medium | G17: Rafay | H17: Complete | J17: 46181 | L17: 46202
B18: June 12 push | C18: Guidelines PDF | D18: Guidelines | E18: keep addtional resources link to pdf | F18: Medium | G18: Rafay | H18: Complete | J18: 46181 | L18: 46202
B19: June 12 push | C19: Update Section | D19: Guidelines | E19: Update the Ready to submit your fan art? section at the bottom of the page. | F19: High | G19: Pratyank | H19: Complete | J19: 46181 | L19: 46202
B20: June 12 push | C20: Page spacing | D20: Book a Demo | E20: Fix Spacing between top of page and nav bar | F20: Medium | G20: Rafay | H20: Complete | J20: 46181 | L20: 46195 | N20: This is fixed on desktop but still showing issues on mobile.
B21: June 12/22 push | C21: Clean up Mobile | D21: Various Pages | E21: Clean up the spacing of headers on each page for Mobile view | F21: High | G21: Pratyank | H21: Complete | J21: 46189 | L21: 46195
B22: June 12/22 push | C22: Mobile page spacing | D22: Book a Demo | E22: Fix spacing on mobile | F22: Medium | G22: Pratyank | H22: Complete | J22: 46181 | L22: 46195 | N22: This is fixed on desktop but still showing issues on mobile.
B23: June 12 push | C23: Combine sections | D23: Book a Demo | E23: Combine the Request Your Brand and Book a Demo section into one. Remove the appt options and scheduling and just add that our Team will be in touch to book a demo and then the demo details from the Book a Demo section | F23: High | G23: Rafay | H23: Complete | J23: 46181 | L23: 46202
B24: June 12 push | C24: Add how did you hear about us | D24: Book a Demo | E24: Add Discord and input field for Other options for how did you hear about us | F24: Low | G24: Rafay -> Pratyank | H24: Complete | J24: 46181 | L24: 46233
C25: Date picker not selecting date | D25: Create Opportunity | E25: Fix error where date picker not selecting date | F25: Medium | G25: Rafay | H25: Not Started
C26: Days Alignment | D26: Create Opportunity | E26: Fix days alignment off | F26: Medium | G26: Rafay | H26: Not Started
B27: 46181 | C27: Fix upload image | D27: Create Opportunity | E27: upload image not working | F27: Medium | G27: Pratyank | H27: Not Started | J27: 46181
C28: Create New Accounts (Brand Owners) | D28: Signup/Login, Super Admin | E28: Fix so we can create new accounts with no issues and login to existing accounts with new issues. | F28: Medium | G28: Dhruv -> Jyotishmoy | H28: Complete | J28: 46188 | L28: 46216
C29: Create New Accounts (Fan Artists) | D29: Signup/Login, Super Admin | E29: Fix so we can create new accounts for fan artists with no issues. | F29: High | G29: Dhruv -> Jyotishmoy | H29: Complete | J29: 46188 | L29: 46216
C30: Test accounts | D30: Signup/Login, Dashboard | E30: Create test accounts for team to login | F30: High | G30: Dhruv -> Jyotishmoy | H30: Complete | J30: 46188
C31: Featured Campaigns style | D31: Home Page | E31: Update featured campaigns to remove the infringement images and template campaigns. Replace with feed of current/live campaigns or preset ones from old/new campaigns. | F31: High | G31: Rafay | H31: Complete | J31: 46188 | L31: 46202
C32: Select Featured Campaigns | D32: Super Admin | E32: Create a function for marking featured campaigns in the Super Admin | F32: High | G32: Dhruv | H32: In Progress | J32: 46188
C33: Featured Campaigns Section | D33: Home Page | E33: Create section for featured campaigns to display | F33: High | G33: Rafay | H33: Complete | J33: 46188 | L33: 46202
C34: Backend Migration | D34: Backend | E34: Migrating Node.js to Nest.js server architecture | F34: Medium | G34: Dhruv, Aakash | H34: Blocked | J34: 46188
C35: Signup Workflow | D35: Signup/Login | E35: Fix the registering of brand owners and fan artists accounts when signing up | F35: Medium | G35: Dhruv, Jyotishmoy | H35: Complete | J35: 46188 | L35: 46216
C36: Shift Manual Auth to Firebase | D36: Auth | E36: Shift the current manual auth apis to firebase sdk instead | F36: High | G36: Aakash | H36: Complete | J36: 46190 | L36: 46198
C37: Add Coolify to VPS | D37: Core/Devops | E37: Shift the projects and db to Coolify instead | F37: High | G37: Aakash | H37: Complete | J37: 46190 | L37: 46202
C38: Make a weekly database backup cron job | D38: DB Backups | E38: Add a weekly automated cron job that makes backup of the db and saves it locally on the VPS itself | F38: Medium | G38: Aakash | H38: Ready for Review | J38: 46190
C39: Update platform T&S date | D39: Terms of Service | E39: Platform Terms of Service date needs to be fixed: Updated June 23, 2026: https://www.modfanofficial.com/legal/terms-and-service | F39: Medium | G39: Pratyank | H39: Complete | J39: 46198 | L39: 46202
C40: Transfer/create submission terms of service and link to each Opportunity/contest page | D40: Terms of Service, Opportunity Pages | E40: Make sure the submissions terms of service has it’s own page and is linked for each contest/opportunity page: https://modfanart.com/pages/submission-terms-and-conditions (need to update “MOD INC.” name to “MOD Fan Official”. create a page for contest submissions terms, you can find the terms data in lib/terms-data/contestSubmissionSections.ts and use the terms-section.tsx component to display it | F40: High | G40: Pratyank | H40: Complete | J40: 46198 | L40: 46202
C41: Authentication for librarians page | D41: Authentication, The Librarians, Opportunty Page | E41: Authentication for the Librarians campaign page. Check if the are logged in for the page. | F41: High | G41: Pratyank | H41: Complete | J41: 46202 | L41: 46216
C42: Remove Welcome Art | D42: Gallery Page | E42: Remove Welcome Artwork in the gallery | F42: Medium | G42: Pratyank | H42: Complete | J42: 46202 | L42: 46244
C43: Update Artwork | D43: Gallery Page | E43: Update the artwork and gallery with past winner art. | F43: Low | G43: Joseph, Pratyank | H43: Blocked
C44: Remove sections in Profile | D44: Profile Settings | E44: Remove API, Billing (can keep hidden for later), and Security (Two Factor Authentication) pages) | F44: Medium | G44: Rafay | H44: Complete | I44: Jyotishmoy | J44: 46202 | L44: 46223
C45: Upoad Profile picture | D45: Profile Settings | E45: Fix upload profile picture | F45: High | G45: Rafay, Pratyank | H45: Complete
C46: Two factor auth | D46: Profile, Security | E46: Setup TFA for users | F46: Low | G46: Aakash | H46: Not Started
C47: User name visibility fix | D47: All | E47: Fix the visibility of the username on top right for all pages in the Hero section | F47: Low | G47: Pratyank | H47: Complete | J47: 46202 | L47: 46223
C48: Fix signup | D48: Sign up/ Login | E48: Fix GoogleAuth for signup and login | F48: High | G48: Jyotishmoy | H48: Complete | J48: 46206 | L48: 46216
C49: Fix Lib contest entry | D49: The Librarians, Submissions | E49: Fix Librarians contest entry button to lead to sign up not submission page | F49: High | G49: Pratyank | H49: Complete | J49: 46206 | L49: 46216
C50: Get Submission flow ready | D50: Submissions, Dashboard | E50: Ensure submission upload page and workflow is functional and ready | F50: High | G50: Jyotishmoy, Aakash | H50: Complete | J50: 46206 | L50: 46216
C51: Link T&S to Lib contest | D51: Terms of Service, The Librarians | E51: Link new Submissions terms and conditions page to Librarians contest | F51: High | G51: Pratyank | H51: Complete | J51: 46209 | L51: 46236
C52: Replace hero image at Signup | D52: Signup/Login | E52: Replace image right side image with logo with new asset provided HERE. | F52: Medium | G52: Pratyank | H52: Complete | J52: 46209 | L52: 46233
C53: Remove for Creators page on mobile | D53: Menu Bar, Mobile | E53: Remove For Creators page in mobile view | F53: Low | G53: Pratyank | H53: Complete | J53: 46209 | L53: 46223
C54: Remove hardcoded parts of the Dashboard | D54: Dashboard clean up | E54: Clean up and remove the sections and numbers that are hardcoded in the dashboards | F54: High | G54: Rafay | H54: Complete | I54: Jyotishmoy | J54: 46211 | L54: 46223
C55: Create Electric Entertainment brand account | D55: Create EE brand Account | E55: Create EE brand account and librrians brand account | F55: High | G55: Joey | H55: Not Started
C56: Fix submission images in dashboard | D56: Dashboard, Submissions | E56: Fixing the images that show up on dashboard for submissions | F56: High | G56: Praytank | H56: Complete | J56: 46214 | L56: 46244
C57: Fix refresh glitch | D57: 404 Page, Login/Signup | E57: When refreshing the website or from a 404 page it automatically brings us to the login/signup page | F57: High | G57: Rafay | H57: Complete | J57: 46214 | L57: 46219
C58: Allow for multi entry submissions | D58: Contests, Submissions | E58: Allow for multiple entries into the contest for submittors | F58: High | G58: Aakash | H58: Complete | J58: 46216
C59: Allow for multi submissions | D59: Contests, Submissions | E59: allow for multiple submissions uploaded at a time | F59: High | G59: Aakash | H59: Complete | J59: 46216
C60: allow for pdf files | D60: Contests, Submissions | E60: allow for pdf files to be uploaded | F60: High | G60: Aakash | H60: Complete | J60: 46216
C61: increase file sizes for submissions | D61: Contests, Submissions | E61: increase file size of submissions allowed to be uploaded | F61: High | G61: Aakash | H61: Complete | J61: 46216
C62: Create superadmin login for team | D62: Super Admin | E62: Create new login credentials for workspace.modfanofficial admin/team dashboard | F62: High | G62: Dhruv | H62: In Progress
C63: Add header and logo nav | D63: Login/Signup | E63: Add the header and logo buttom to head back to main page from the dashboard, login/signup page, to easily navigate back to main page. | F63: Low | G63: Rafay | H63: In Progress | J63: 46216
C64: Individual submission pages | D64: Dashboard, Submissions, Contests | E64: Build out the individual submission/artwork page with all notes and details | F64: Medium | G64: Rafay | H64: Complete | J64: 46216 | L64: 46244
C65: Fix submission tags | D65: Contests, Submissions | E65: Submission page tags section is not working | F65: Medium | G65: Pratyank | H65: Complete | J65: 46216 | L65: 46233
C66: Add description and note to contest entry | D66: Contests, Submissions | E66: Add a Note section to the submission page | F66: Medium | G66: Praytank | H66: Complete | J66: 46216 | L66: 46223
C67: Setup full contest and submission flow backend | D67: Contests, Submissions, Dashboard | E67: Create proper backend flow for creating new contests and submissions flow correctly connected to it. Review gaps Jyotishmoy shared and what is needed left. | F67: High | G67: Aakash, Jyotishmoy, Pratyank | H67: Ready for Review | J67: 46214
C68: Link artists and brand owners with contest ID | D68: Contests, Submissions | E68: How to link to artists and brand owners (through the submission?), contest ID to link them all? | F68: Medium | G68: Aakash, Jyotishmoy, Pratyank | H68: Ready for Review | J68: 46214
C69: Create viewable approved artwork page | D69: Submisions, Dashboard | E69: Where do artwork go and are viewable once approved on brand side. | F69: Medium | G69: Aakash, Jyotishmoy, Pratyank, Rafay | J69: 46214
C70: Link EE account to Librarians contest | D70: Contests | E70: Link new EE account connect the Librarians contest to them to see and setup for approvals/judging. | F70: Medium | G70: Aakash | H70: Blocked | J70: 46216
C71: Switch domain to hostinger | D71: Server, Domain | E71: Connect domain to hostinger to move away from vercel | F71: High | G71: Aakash | H71: Complete | J71: 46202 | L71: 46203
C72: Fix submission showing in Gallery | D72: Gallery, Backend | E72: Fixing so submissions don't automatically show up in the main gallery for everyone, they should only show approved and licesned artwork there | F72: High | G72: Pratyank | H72: Ready for Review | J72: 46219
C73: Fix contest submit art button to dashboard for logged in | D73: Contest Page, Dashboard, Login | E73: if logged in the submit art on contest page takes you to the login page, would be best to take it to dashboard directly to the submit page | F73: Medium | G73: Rafay | H73: Complete
C74: Login Issues with firebase | D74: Login, User | E74: User getting logged out and also having login in issues using google auth. Seems to be a firebase issue. | F74: Medium | G74: Aakash | H74: Complete | J74: 46219
C75: Fix Dashboard Setting button | D75: Dashboard | E75: Dashboard setting button on the bottom is fixed and connected to settings page. | F75: Low | G75: rafay | J75: 46219
C76: Update dashboard top right menu to full one | D76: Dashboard | E76: The dropdown menu at top right when clicking name is not appear in the dashboard, have it reappear there | F76: Low | G76: Rafay | J76: 46219
C77: Upload Favicon | D77: Favicon | E77: favicon is missing | F77: Low
C78: Fix timezone options | D78: Settings, Account | E78: Update Settings so you can choose EST and other timezones. | F78: Low | G78: Rafay
C79: Fix failed to create artwork issue | D79: Submissions, The Librarians | E79: Failed to create artwork issue coming up for user on mobile and desktop | F79: High | G79: Aakash | H79: Complete
C80: Complete migration away from AWS | D80: Server | E80: Full complete migration from AWS to Hostinger or other s3 services | F80: High | H80: Complete | J80: 46223 | L80: 46233
C81: Dashboard welcome back name | D81: Dashboard | E81: Dashboard welcome back name hardcoded | F81: Low | G81: Rafay | H81: Complete | J81: 46223
C82: Old contest page link | D82: Contests | E82: linking to old contest page | F82: Medium | G82: Rafay | H82: Blocked
C83: Dashboard - View All Submissions | D83: Brand Manager Dashboard | E83: The brand account dashboard currently caps at ~20 submissions with no way to see the rest | F83: High | G83: Pratyank | H83: Complete | J83: 46233 | L83: 46244
C84: Submission Detail View - Full Image + Form Metadata | D84: Brand Manager Dashboard | E84: Clicking a submission on the dashboard should open a full detail view showing the full-size artwork image plus all metadata | F84: High | G84: Pratyank | H84: Complete | J84: 46233 | L84: 46244
C85: Fix dashboard images | D85: Dashboard | E85: ⁠ ⁠Fix images showing now loading/showing on the platform dashboards (need to be able to see the entries). | F85: High | G85: Rafay | H85: Complete | J85: 46214 | L85: 46244
C86: Super admin credentials | D86: Super Admin | E86: Access to the mod super admin workspace. Need the new credentials for this so we can see all users, brand requests, and inquires that have come in through the website. | F86: High | G86: Dhruv | J86: 46214
C87: Submission page details | D87: Submissions | E87: Each submission page that shows that submission image or multiple images, all the inputs from the submission form, and the AI check results. | F87: High | G87: Rafay/Pratyank | H87: Blocked | J87: 46233
C88: Prepare judging system | D88: Judging | E88: ⁠Prepare the judging system for when librarians contest ends. We will need to send the judging links to the librarians team. | F88: High | G88: Rafay | H88: Complete | J88: 46233 | L88: 46258
C89: Judging backend endpoints | D89: Backend/Judging | E89: Fix backend enpoints for juding system | F89: High | G89: Pratyank | H89: Complete | J89: 46244 | L89: 46258
C90: PDF image preview | D90: Submissions | E90: pdf image preview for submissions needs to be fixed, replace with placeholder PDF image so it's not showing like an eerror | F90: Medium | G90: Rafay | H90: Complete | J90: 46244 | L90: 46265
C91: Judging next phase | D91: Judging | E91: Complete next phase of judging to show results, select final winners, and generate shareable link to view the top 10 (internal link for brand team/final look over). | G91: Pratyank | H91: Complete | J91: 46251 | L91: 46258
C92: AI system UI | D92: Frontend/AI | E92: Create frontend/UI of the AI system and integrating the script into our system. | G92: Aakash, Pratyank, Rafay | J92: 46258
C93: Marketplace plan | D93: Marketplace | E93: Next phase Marketplace plan creation and implementation | G93: Dhruv | J93: 46251
C94: Copy judging password | D94: Judging | E94: Unable to copy Judging password from popup that appears when creating juding account. | G94: Pratyank | H94: Complete | J94: 46251 | L94: 46258
C95: Brand account creation error | D95: Super Admin/Judging | E95: Error appeared when creating brand account through juding link: Submission failed: Collumn "contact_email"of relation "brand_verification_requests" does not exist | G95: Pratyank | H95: Complete
C96: Login page standard | D96: Login/Backend | E96: Fix login page and backend to industry standard | F96: Low | G96: Dhruv | J96: 46258
C97: Update contest results | D97: Contests | E97: Update contest results with finalized licensing and selected artwork | G97: Pratyank | H97: Merged | J97: 46261
C98: AI system integration | D98: AI | E98: Connect with Aakash on AI system and figure out integration into the front end, for submission checks for campaigns and always on submissions | G98: Rafay | J98: 46258
C99: Marketplace tasks | D99: Marketplace | E99: Decide and assign tasks for Marketplace roll out | G99: Dhruv | J99: 46258
C100: Licensing workflow doc | D100: Licensing | E100: Assess licensing workflow and create doc to get team aligned | G100: Dhruv | H100: Complete | J100: 46258 | L100: 46261
C101: Github security filtration | D101: Github/Security | E101: Github filtration to clean up security issues. | G101: Dhruv | H101: Complete | J101: 46258
...

Sheet Weekly Summary
B1: Weekly Summary Dashboard
B3: Total Open Tasks | C3: Tasks In Progress | D3: Tasks Ready for Review
B4: =COUNTIFS('Log Tracker'!H4:H104, "<>Complete", 'Log Tracker'!H4:H104, "<>Merged", 'Log Tracker'!H4:H104, "<>") -> 18 | C4: =COUNTIF('Log Tracker'!H4:H104, "In Progress") -> 4 | D4: =COUNTIF('Log Tracker'!H4:H104, "Ready for Review") -> 4
B5: Tasks Merged | C5: Tasks Completed | D5: Completion Rate %
B6: =COUNTIF('Log Tracker'!H4:H104, "Merged") -> 1 | C6: =COUNTIF('Log Tracker'!H4:H104, "Complete") -> 69 | D6: =IF(COUNTA('Log Tracker'!H4:H104)=0, 0, (COUNTIF('Log Tracker'!H4:H104, "Complete") + COUNTIF('Log Tracker'!H4:H104, "Merged")) / COUNTA('Log Tracker'!H4:H104)) -> 0.79545455
B9: Week | C9: Team Member | D9: Tasks Assigned | E9: Tasks Completed | F9: Tasks Merged | G9: Tasks Carried Over | H9: Major Accomplishments | I9: Blockers | J9: Support Needed Next Week
B10: =IFERROR(__xludf.DUMMYFUNCTION("LET(tasks, 'Log Tracker'!C4:C1000, assignees, 'Log Tracker'!G4:G1000, status, 'Log Tracker'!H4:H1000, compDates, 'Log Tracker'!L4:L1000, blockers, 'Log Tracker'!O4:O1000, carry, 'Log Tracker'!Q4:Q1000, uniqueWeeks, SORT(UNIQUE(FILTER(compDates, compDates<"&">""""))), result, REDUCE({"""", """", """", """", """", """", """", """", """"}, uniqueWeeks, LAMBDA(acc, wk, LET(weekTasks, FILTER(tasks, compDates=wk), weekAssignees, FILTER(assignees, compDates=wk), weekStatus, FILTER(status, compDates=wk), weekBlocker"&"s, FILTER(blockers, compDates=wk), weekCarry, FILTER(carry, compDates=wk), assignedCount, COUNTA(weekTasks), completedCount, COUNTIF(weekStatus, ""Complete""), mergedCount, COUNTIF(weekStatus, ""Merged""), carryCount, COUNTIF(weekCarry, ""Y""), teamMember"&"s, TEXTJOIN("", "", TRUE, UNIQUE(weekAssignees)), accomplishments, TEXTJOIN("" | "", TRUE, weekTasks), blockersText, IFERROR(TEXTJOIN("" | "", TRUE, FILTER(weekBlockers, weekBlockers<>""N/A"", weekBlockers<>"""")), """"), VSTACK(acc, {wk, teamMembers, ass"&"ignedCount, completedCount, mergedCount, carryCount, accomplishments, blockersText, """"})))) , CHOOSEROWS(result, SEQUENCE(ROWS(result)-1, 1, 2)))"),46174) -> 46174 | C10: =IFERROR(__xludf.DUMMYFUNCTION("""COMPUTED_VALUE"""),"Joey") -> Joey | D10: =IFERROR(__xludf.DUMMYFUNCTION("""COMPUTED_VALUE"""),1) -> 1 | E10: =IFERROR(__xludf.DUMMYFUNCTION("""COMPUTED_VALUE"""),1) -> 1 | F10: =IFERROR(__xludf.DUMMYFUNCTION("""COMPUTED_VALUE"""),0) -> 0 | G10: =IFERROR(__xludf.DUMMYFUNCTION("""COMPUTED_VALUE"""),1) -> 1 | H10: =IFERROR(__xludf.DUMMYFUNCTION("""COMPUTED_VALUE"""),"Dev Log & Tracker") -> Dev Log & Tracker | I10: =IFERROR(__xludf.DUMMYFUNCTION("""COMPUTED_VALUE"""),"") | J10: =IFERROR(__xludf.DUMMYFUNCTION("""COMPUTED_VALUE"""),"")
B11: =IFERROR(__xludf.DUMMYFUNCTION("""COMPUTED_VALUE"""),46181) -> 46181 | C11: =IFERROR(__xludf.DUMMYFUNCTION("""COMPUTED_VALUE"""),"Rafay") -> Rafay | D11: =IFERROR(__xludf.DUMMYFUNCTION("""COMPUTED_VALUE"""),4) -> 4 | E11: =IFERROR(__xludf.DUMMYFUNCTION("""COMPUTED_VALUE"""),4) -> 4 | F11: =IFERROR(__xludf.DUMMYFUNCTION("""COMPUTED_VALUE"""),0) -> 0 | G11: =IFERROR(__xludf.DUMMYFUNCTION("""COMPUTED_VALUE"""),0) -> 0 | H11: =IFERROR(__xludf.DUMMYFUNCTION("""COMPUTED_VALUE"""),"Double footer | Update Buttons | Artist Logos | Nav Bar update") -> Double footer | Update Buttons | Artist Logos | Nav Bar update | I11: =IFERROR(__xludf.DUMMYFUNCTION("""COMPUTED_VALUE"""),"") | J11: =IFERROR(__xludf.DUMMYFUNCTION("""COMPUTED_VALUE"""),"")
B12: =IFERROR(__xludf.DUMMYFUNCTION("""COMPUTED_VALUE"""),46195) -> 46195 | C12: =IFERROR(__xludf.DUMMYFUNCTION("""COMPUTED_VALUE"""),"Rafay, Pratyank") -> Rafay, Pratyank | D12: =IFERROR(__xludf.DUMMYFUNCTION("""COMPUTED_VALUE"""),3) -> 3 | E12: =IFERROR(__xludf.DUMMYFUNCTION("""COMPUTED_VALUE"""),3) -> 3 | F12: =IFERROR(__xludf.DUMMYFUNCTION("""COMPUTED_VALUE"""),0) -> 0 | G12: =IFERROR(__xludf.DUMMYFUNCTION("""COMPUTED_VALUE"""),0) -> 0 | H12: =IFERROR(__xludf.DUMMYFUNCTION("""COMPUTED_VALUE"""),"Page spacing | Clean up Mobile | Mobile page spacing") -> Page spacing | Clean up Mobile | Mobile page spacing | I12: =IFERROR(__xludf.DUMMYFUNCTION("""COMPUTED_VALUE"""),"") | J12: =IFERROR(__xludf.DUMMYFUNCTION("""COMPUTED_VALUE"""),"")
B13: =IFERROR(__xludf.DUMMYFUNCTION("""COMPUTED_VALUE"""),46198) -> 46198 | C13: =IFERROR(__xludf.DUMMYFUNCTION("""COMPUTED_VALUE"""),"Aakash") -> Aakash | D13: =IFERROR(__xludf.DUMMYFUNCTION("""COMPUTED_VALUE"""),1) -> 1 | E13: =IFERROR(__xludf.DUMMYFUNCTION("""COMPUTED_VALUE"""),1) -> 1 | F13: =IFERROR(__xludf.DUMMYFUNCTION("""COMPUTED_VALUE"""),0) -> 0 | G13: =IFERROR(__xludf.DUMMYFUNCTION("""COMPUTED_VALUE"""),0) -> 0 | H13: =IFERROR(__xludf.DUMMYFUNCTION("""COMPUTED_VALUE"""),"Shift Manual Auth to Firebase") -> Shift Manual Auth to Firebase | I13: =IFERROR(__xludf.DUMMYFUNCTION("""COMPUTED_VALUE"""),"") | J13: =IFERROR(__xludf.DUMMYFUNCTION("""COMPUTED_VALUE"""),"")
B14: =IFERROR(__xludf.DUMMYFUNCTION("""COMPUTED_VALUE"""),46202) -> 46202 | C14: =IFERROR(__xludf.DUMMYFUNCTION("""COMPUTED_VALUE"""),"Pratyank, Rafay, Aakash") -> Pratyank, Rafay, Aakash | D14: =IFERROR(__xludf.DUMMYFUNCTION("""COMPUTED_VALUE"""),11) -> 11 | E14: =IFERROR(__xludf.DUMMYFUNCTION("""COMPUTED_VALUE"""),11) -> 11 | F14: =IFERROR(__xludf.DUMMYFUNCTION("""COMPUTED_VALUE"""),0) -> 0 | G14: =IFERROR(__xludf.DUMMYFUNCTION("""COMPUTED_VALUE"""),0) -> 0 | H14: =IFERROR(__xludf.DUMMYFUNCTION("""COMPUTED_VALUE"""),"Update Image | Remove some sections | Discord link | Guidelines PDF | Update Section | Combine sections | Featured Campaigns style | Featured Campaigns Section | Add Coolify to VPS | Update platform T&S date | Transfer/create submission terms of service"&" and link to each Opportunity/contest page") -> Update Image | Remove some sections | Discord link | Guidelines PDF | Update Section | Combine sections | Featured Campaigns style | Featured Campaigns Section | Add Coolify to VPS | Update platform T&S date | Transfer/create submission terms of service and link to each Opportunity/contest page | I14: =IFERROR(__xludf.DUMMYFUNCTION("""COMPUTED_VALUE"""),"") | J14: =IFERROR(__xludf.DUMMYFUNCTION("""COMPUTED_VALUE"""),"")
B15: =IFERROR(__xludf.DUMMYFUNCTION("""COMPUTED_VALUE"""),46203) -> 46203 | C15: =IFERROR(__xludf.DUMMYFUNCTION("""COMPUTED_VALUE"""),"Aakash") -> Aakash | D15: =IFERROR(__xludf.DUMMYFUNCTION("""COMPUTED_VALUE"""),1) -> 1 | E15: =IFERROR(__xludf.DUMMYFUNCTION("""COMPUTED_VALUE"""),1) -> 1 | F15: =IFERROR(__xludf.DUMMYFUNCTION("""COMPUTED_VALUE"""),0) -> 0 | G15: =IFERROR(__xludf.DUMMYFUNCTION("""COMPUTED_VALUE"""),0) -> 0 | H15: =IFERROR(__xludf.DUMMYFUNCTION("""COMPUTED_VALUE"""),"Switch domain to hostinger") -> Switch domain to hostinger | I15: =IFERROR(__xludf.DUMMYFUNCTION("""COMPUTED_VALUE"""),"") | J15: =IFERROR(__xludf.DUMMYFUNCTION("""COMPUTED_VALUE"""),"")
B16: =IFERROR(__xludf.DUMMYFUNCTION("""COMPUTED_VALUE"""),46216) -> 46216 | C16: =IFERROR(__xludf.DUMMYFUNCTION("""COMPUTED_VALUE"""),"Dhruv -> Jyotishmoy, Dhruv, Jyotishmoy, Pratyank, Jyotishmoy, Jyotishmoy, Aakash") -> Dhruv -> Jyotishmoy, Dhruv, Jyotishmoy, Pratyank, Jyotishmoy, Jyotishmoy, Aakash | D16: =IFERROR(__xludf.DUMMYFUNCTION("""COMPUTED_VALUE"""),7) -> 7 | E16: =IFERROR(__xludf.DUMMYFUNCTION("""COMPUTED_VALUE"""),7) -> 7 | F16: =IFERROR(__xludf.DUMMYFUNCTION("""COMPUTED_VALUE"""),0) -> 0 | G16: =IFERROR(__xludf.DUMMYFUNCTION("""COMPUTED_VALUE"""),0) -> 0 | H16: =IFERROR(__xludf.DUMMYFUNCTION("""COMPUTED_VALUE"""),"Create New Accounts (Brand Owners) | Create New Accounts (Fan Artists) | Signup Workflow | Authentication for librarians page | Fix signup | Fix Lib contest entry | Get Submission flow ready") -> Create New Accounts (Brand Owners) | Create New Accounts (Fan Artists) | Signup Workflow | Authentication for librarians page | Fix signup | Fix Lib contest entry | Get Submission flow ready | I16: =IFERROR(__xludf.DUMMYFUNCTION("""COMPUTED_VALUE"""),"") | J16: =IFERROR(__xludf.DUMMYFUNCTION("""COMPUTED_VALUE"""),"")
B17: =IFERROR(__xludf.DUMMYFUNCTION("""COMPUTED_VALUE"""),46219) -> 46219 | C17: =IFERROR(__xludf.DUMMYFUNCTION("""COMPUTED_VALUE"""),"Rafay") -> Rafay | D17: =IFERROR(__xludf.DUMMYFUNCTION("""COMPUTED_VALUE"""),1) -> 1 | E17: =IFERROR(__xludf.DUMMYFUNCTION("""COMPUTED_VALUE"""),1) -> 1 | F17: =IFERROR(__xludf.DUMMYFUNCTION("""COMPUTED_VALUE"""),0) -> 0 | G17: =IFERROR(__xludf.DUMMYFUNCTION("""COMPUTED_VALUE"""),0) -> 0 | H17: =IFERROR(__xludf.DUMMYFUNCTION("""COMPUTED_VALUE"""),"Fix refresh glitch ") -> Fix refresh glitch | I17: =IFERROR(__xludf.DUMMYFUNCTION("""COMPUTED_VALUE"""),"") | J17: =IFERROR(__xludf.DUMMYFUNCTION("""COMPUTED_VALUE"""),"")
B18: =IFERROR(__xludf.DUMMYFUNCTION("""COMPUTED_VALUE"""),46223) -> 46223 | C18: =IFERROR(__xludf.DUMMYFUNCTION("""COMPUTED_VALUE"""),"Rafay, Pratyank, Praytank") -> Rafay, Pratyank, Praytank | D18: =IFERROR(__xludf.DUMMYFUNCTION("""COMPUTED_VALUE"""),5) -> 5 | E18: =IFERROR(__xludf.DUMMYFUNCTION("""COMPUTED_VALUE"""),5) -> 5 | F18: =IFERROR(__xludf.DUMMYFUNCTION("""COMPUTED_VALUE"""),0) -> 0 | G18: =IFERROR(__xludf.DUMMYFUNCTION("""COMPUTED_VALUE"""),0) -> 0 | H18: =IFERROR(__xludf.DUMMYFUNCTION("""COMPUTED_VALUE"""),"Remove sections in Profile | User name visibility fix | Remove for Creators page on mobile | Remove hardcoded parts of the Dashboard | Add description and note to contest entry") -> Remove sections in Profile | User name visibility fix | Remove for Creators page on mobile | Remove hardcoded parts of the Dashboard | Add description and note to contest entry | I18: =IFERROR(__xludf.DUMMYFUNCTION("""COMPUTED_VALUE"""),"") | J18: =IFERROR(__xludf.DUMMYFUNCTION("""COMPUTED_VALUE"""),"")
B19: =IFERROR(__xludf.DUMMYFUNCTION("""COMPUTED_VALUE"""),46233) -> 46233 | C19: =IFERROR(__xludf.DUMMYFUNCTION("""COMPUTED_VALUE"""),"Rafay -> Pratyank, Pratyank") -> Rafay -> Pratyank, Pratyank | D19: =IFERROR(__xludf.DUMMYFUNCTION("""COMPUTED_VALUE"""),4) -> 4 | E19: =IFERROR(__xludf.DUMMYFUNCTION("""COMPUTED_VALUE"""),4) -> 4 | F19: =IFERROR(__xludf.DUMMYFUNCTION("""COMPUTED_VALUE"""),0) -> 0 | G19: =IFERROR(__xludf.DUMMYFUNCTION("""COMPUTED_VALUE"""),0) -> 0 | H19: =IFERROR(__xludf.DUMMYFUNCTION("""COMPUTED_VALUE"""),"Add how did you hear about us | Replace hero image at Signup | Fix submission tags | Complete migration away from AWS") -> Add how did you hear about us | Replace hero image at Signup | Fix submission tags | Complete migration away from AWS | I19: =IFERROR(__xludf.DUMMYFUNCTION("""COMPUTED_VALUE"""),"") | J19: =IFERROR(__xludf.DUMMYFUNCTION("""COMPUTED_VALUE"""),"")
B20: =IFERROR(__xludf.DUMMYFUNCTION("""COMPUTED_VALUE"""),46236) -> 46236 | C20: =IFERROR(__xludf.DUMMYFUNCTION("""COMPUTED_VALUE"""),"Pratyank") -> Pratyank | D20: =IFERROR(__xludf.DUMMYFUNCTION("""COMPUTED_VALUE"""),1) -> 1 | E20: =IFERROR(__xludf.DUMMYFUNCTION("""COMPUTED_VALUE"""),1) -> 1 | F20: =IFERROR(__xludf.DUMMYFUNCTION("""COMPUTED_VALUE"""),0) -> 0 | G20: =IFERROR(__xludf.DUMMYFUNCTION("""COMPUTED_VALUE"""),0) -> 0 | H20: =IFERROR(__xludf.DUMMYFUNCTION("""COMPUTED_VALUE"""),"Link T&S to Lib contest") -> Link T&S to Lib contest | I20: =IFERROR(__xludf.DUMMYFUNCTION("""COMPUTED_VALUE"""),"") | J20: =IFERROR(__xludf.DUMMYFUNCTION("""COMPUTED_VALUE"""),"")
B21: =IFERROR(__xludf.DUMMYFUNCTION("""COMPUTED_VALUE"""),46244) -> 46244 | C21: =IFERROR(__xludf.DUMMYFUNCTION("""COMPUTED_VALUE"""),"Pratyank, Praytank, Rafay") -> Pratyank, Praytank, Rafay | D21: =IFERROR(__xludf.DUMMYFUNCTION("""COMPUTED_VALUE"""),6) -> 6 | E21: =IFERROR(__xludf.DUMMYFUNCTION("""COMPUTED_VALUE"""),6) -> 6 | F21: =IFERROR(__xludf.DUMMYFUNCTION("""COMPUTED_VALUE"""),0) -> 0 | G21: =IFERROR(__xludf.DUMMYFUNCTION("""COMPUTED_VALUE"""),0) -> 0 | H21: =IFERROR(__xludf.DUMMYFUNCTION("""COMPUTED_VALUE"""),"Remove Welcome Art | Fix submission images in dashboard | Individual submission pages | Dashboard - View All Submissions | Submission Detail View - Full Image + Form Metadata | Fix dashboard images") -> Remove Welcome Art | Fix submission images in dashboard | Individual submission pages | Dashboard - View All Submissions | Submission Detail View - Full Image + Form Metadata | Fix dashboard images | I21: =IFERROR(__xludf.DUMMYFUNCTION("""COMPUTED_VALUE"""),"") | J21: =IFERROR(__xludf.DUMMYFUNCTION("""COMPUTED_VALUE"""),"")
B22: =IFERROR(__xludf.DUMMYFUNCTION("""COMPUTED_VALUE"""),46258) -> 46258 | C22: =IFERROR(__xludf.DUMMYFUNCTION("""COMPUTED_VALUE"""),"Rafay, Pratyank") -> Rafay, Pratyank | D22: =IFERROR(__xludf.DUMMYFUNCTION("""COMPUTED_VALUE"""),4) -> 4 | E22: =IFERROR(__xludf.DUMMYFUNCTION("""COMPUTED_VALUE"""),4) -> 4 | F22: =IFERROR(__xludf.DUMMYFUNCTION("""COMPUTED_VALUE"""),0) -> 0 | G22: =IFERROR(__xludf.DUMMYFUNCTION("""COMPUTED_VALUE"""),0) -> 0 | H22: =IFERROR(__xludf.DUMMYFUNCTION("""COMPUTED_VALUE"""),"Prepare judging system | Judging backend endpoints | Judging next phase | Copy judging password") -> Prepare judging system | Judging backend endpoints | Judging next phase | Copy judging password | I22: =IFERROR(__xludf.DUMMYFUNCTION("""COMPUTED_VALUE"""),"") | J22: =IFERROR(__xludf.DUMMYFUNCTION("""COMPUTED_VALUE"""),"")
B23: =IFERROR(__xludf.DUMMYFUNCTION("""COMPUTED_VALUE"""),46261) -> 46261 | C23: =IFERROR(__xludf.DUMMYFUNCTION("""COMPUTED_VALUE"""),"Dhruv") -> Dhruv | D23: =IFERROR(__xludf.DUMMYFUNCTION("""COMPUTED_VALUE"""),1) -> 1 | E23: =IFERROR(__xludf.DUMMYFUNCTION("""COMPUTED_VALUE"""),0) -> 0 | F23: =IFERROR(__xludf.DUMMYFUNCTION("""COMPUTED_VALUE"""),0) -> 0 | G23: =IFERROR(__xludf.DUMMYFUNCTION("""COMPUTED_VALUE"""),0) -> 0 | H23: =IFERROR(__xludf.DUMMYFUNCTION("""COMPUTED_VALUE"""),"Licensing workflow doc") -> Licensing workflow doc | I23: =IFERROR(__xludf.DUMMYFUNCTION("""COMPUTED_VALUE"""),"") | J23: =IFERROR(__xludf.DUMMYFUNCTION("""COMPUTED_VALUE"""),"")
B24: =IFERROR(__xludf.DUMMYFUNCTION("""COMPUTED_VALUE"""),46265) -> 46265 | C24: =IFERROR(__xludf.DUMMYFUNCTION("""COMPUTED_VALUE"""),"Rafay") -> Rafay | D24: =IFERROR(__xludf.DUMMYFUNCTION("""COMPUTED_VALUE"""),1) -> 1 | E24: =IFERROR(__xludf.DUMMYFUNCTION("""COMPUTED_VALUE"""),1) -> 1 | F24: =IFERROR(__xludf.DUMMYFUNCTION("""COMPUTED_VALUE"""),0) -> 0 | G24: =IFERROR(__xludf.DUMMYFUNCTION("""COMPUTED_VALUE"""),0) -> 0 | H24: =IFERROR(__xludf.DUMMYFUNCTION("""COMPUTED_VALUE"""),"PDF image preview") -> PDF image preview | I24: =IFERROR(__xludf.DUMMYFUNCTION("""COMPUTED_VALUE"""),"") | J24: =IFERROR(__xludf.DUMMYFUNCTION("""COMPUTED_VALUE"""),"")
